ravepaypysdk/__init__.py
ravepaypysdk/api.py
ravepaypysdk/api_exceptions.py
ravepaypysdk/helpers.py
ravepaypysdk/resources.py
ravepaypysdk/utils/__init__.py
ravepaypysdk/utils/encryption.py
ravepaypysdk/utils/rave_utils.py
ravepaypysdk-1.0.2.dist-info/METADATA
ravepaypysdk-1.0.2.dist-info/RECORD
ravepaypysdk-1.0.2.dist-info/WHEEL
ravepaypysdk-1.0.2.dist-info/top_level.txt
