Metadata-Version: 2.1
Name: ravepaypysdk
Version: 1.0.2
Summary: A Python library to consume the RavePay API
Home-page: https://github.com/johnchuks/ravepay-python-sdk
Author: Johnbosco Ohia
Author-email: johnboscoohia@gmail.com
License: MIT
Keywords: ravepay python library
Platform: UNKNOWN
Classifier: Development Status :: 4 - Beta
Classifier: Intended Audience :: Developers
Classifier: License :: OSI Approved :: MIT License
Classifier: Programming Language :: Python :: 2
Classifier: Programming Language :: Python :: 2.6
Classifier: Programming Language :: Python :: 2.7
Classifier: Programming Language :: Python :: 3
Classifier: Programming Language :: Python :: 3.3
Classifier: Programming Language :: Python :: 3.4
Classifier: Programming Language :: Python :: 3.5
Classifier: Programming Language :: Python :: 3.6
Provides-Extra: test
Requires-Dist: requests
Requires-Dist: pycrypto
Provides-Extra: test
Requires-Dist: coverage; extra == 'test'
